clip_image_detector-0.1.0.dist-info/licenses/LICENSE
clipimagedetector/__init__.py
clipimagedetector/app.py
clipimagedetector/version.py
clip_image_detector-0.1.0.dist-info/METADATA
clip_image_detector-0.1.0.dist-info/WHEEL
clip_image_detector-0.1.0.dist-info/top_level.txt
clip_image_detector-0.1.0.dist-info/RECORD
