Metadata-Version: 2.4
Name: clip-image-detector
Version: 0.1.0
Summary: Zero-Shot Image Detection using OpenAI CLIP
Author: fake-babu
Author-email: fake-babu <apunfake.babu@gmail.com>
License: MIT License
Keywords: clip,image-detection,machine-learning,computer-vision
Classifier: Development Status :: 3 - Alpha
Classifier: Intended Audience :: Developers
Classifier: License :: OSI Approved :: MIT License
Classifier: Programming Language :: Python :: 3
Classifier: Programming Language :: Python :: 3.8
Classifier: Programming Language :: Python :: 3.9
Requires-Python: >=3.8
License-File: LICENSE
Requires-Dist: streamlit>=1.0.0
Requires-Dist: torch>=1.7.1
Requires-Dist: Pillow>=8.0.0
Requires-Dist: numpy>=1.19.0
Requires-Dist: ftfy
Requires-Dist: regex
Requires-Dist: tqdm
Dynamic: license-file
